{
  "generated_at": "2026-05-12T11:30:59",
  "source_manifest": "/Users/ezrajohnston/Desktop/unity/Immersive Environments/Assets/StreamingAssets/curated-props.json",
  "overlay": "/Users/ezrajohnston/Desktop/unity/Immersive Environments/Assets/StreamingAssets/curation_overrides.json",
  "counts": {
    "base_props": 1581,
    "game_ready": 1581,
    "non_ready": 0,
    "reviewed_ids": 6026,
    "removed_ids": 4444
  },
  "integrity": {
    "duplicate_ids_in_base": [],
    "duplicate_id_count": 0,
    "reviewed_not_in_manifest_sample": [
      "css_characters_counterterrorist",
      "css_characters_hostage_01",
      "css_characters_hostage_02",
      "css_characters_hostage_03",
      "css_characters_hostage_04",
      "css_combine_camera_combine_camera",
      "css_editor_air_node",
      "css_editor_air_node_hint",
      "css_editor_axis_helper",
      "css_editor_axis_helper_thick",
      "css_editor_camera",
      "css_editor_climb_node",
      "css_editor_cone_helper",
      "css_editor_ground_node",
      "css_editor_ground_node_hint",
      "css_editor_node_hint",
      "css_editor_overlay_helper",
      "css_editor_playerstart",
      "css_editor_scriptedsequence",
      "css_editor_spot",
      "css_editor_spot_cone",
      "css_effects_combineball",
      "css_effects_teleporttrail",
      "css_effects_teleporttrail_alyx",
      "css_extras_info_speech",
      "css_items_cs_gift",
      "css_perftest_gman",
      "css_perftest_grass_tuft_001",
      "css_perftest_grass_tuft_001a",
      "css_perftest_grass_tuft_001b",
      "css_perftest_grass_tuft_003a",
      "css_perftest_grass_tuft_004a",
      "css_perftest_grass_tuft_004b",
      "css_perftest_grass_tuft_004c",
      "css_perftest_grass_tuft_004d",
      "css_perftest_rocksground01c",
      "css_perftest_rocksground01d",
      "css_perftest_rocksground01e",
      "css_perftest_rocksground02a",
      "css_perftest_rocksground02b",
      "css_perftest_rocksground02c",
      "css_props_borealis_mooring_cleat01",
      "css_props_building_details_building_tem002_window01",
      "css_props_building_details_building_tem002_window01_bars",
      "css_props_building_details_courtyard_template002_window",
      "css_props_combine_breenconsole",
      "css_props_combine_breenlight",
      "css_props_combine_breenpod_inner",
      "css_props_combine_bunker_gun01",
      "css_props_combine_combine_barricade_bracket01a"
    ],
    "reviewed_not_in_manifest_count": 4445,
    "game_ready_missing_glb_sample": [],
    "game_ready_missing_glb_count": 0
  },
  "outputs": {
    "game_ready": "/Users/ezrajohnston/Desktop/unity/Immersive Environments/Assets/StreamingAssets/curated-props.game-ready.json",
    "non_ready": "/Users/ezrajohnston/Desktop/unity/Immersive Environments/Assets/StreamingAssets/curated-props.non-ready.json"
  }
}